setup.py
cal_star.egg-info/PKG-INFO
cal_star.egg-info/SOURCES.txt
cal_star.egg-info/dependency_links.txt
cal_star.egg-info/requires.txt
cal_star.egg-info/top_level.txt
src/cal_star/__init__.py
src/cal_star/sc_cluster.py
src/cal_star/sc_photometry.py
src/cal_star/sc_skymap.py
src/cal_star/sc_sp.py
src/cal_star/demo/demo.ipynb
src/cal_star/demo/demo2_cluster.ipynb
src/cal_star/demo/demo2_cluster.py
src/cal_star/refdata/1d_sp/Hamuy1992/CD -32 9927.dat
src/cal_star/refdata/1d_sp/Hamuy1992/CD -34 241.dat
src/cal_star/refdata/1d_sp/Hamuy1992/EG 21.dat
src/cal_star/refdata/1d_sp/Hamuy1992/EG 274.dat
src/cal_star/refdata/1d_sp/Hamuy1992/Feige 110.dat
src/cal_star/refdata/1d_sp/Hamuy1992/Feige 56.dat
src/cal_star/refdata/1d_sp/Hamuy1992/Hiltner 600.dat
src/cal_star/refdata/1d_sp/Hamuy1992/LTT 1020.dat
src/cal_star/refdata/1d_sp/Hamuy1992/LTT 1788.dat
src/cal_star/refdata/1d_sp/Hamuy1992/LTT 2415.dat
src/cal_star/refdata/1d_sp/Hamuy1992/LTT 3218.dat
src/cal_star/refdata/1d_sp/Hamuy1992/LTT 3864.dat
src/cal_star/refdata/1d_sp/Hamuy1992/LTT 4364.dat
src/cal_star/refdata/1d_sp/Hamuy1992/LTT 4816.dat
src/cal_star/refdata/1d_sp/Hamuy1992/LTT 6248.dat
src/cal_star/refdata/1d_sp/Hamuy1992/LTT 7379.dat
src/cal_star/refdata/1d_sp/Hamuy1992/LTT 7987.dat
src/cal_star/refdata/1d_sp/Hamuy1992/LTT 9239.dat
src/cal_star/refdata/1d_sp/Hamuy1992/LTT 9491.dat
src/cal_star/refdata/1d_sp/Hamuy1992/hr1544.dat
src/cal_star/refdata/1d_sp/Hamuy1992/hr3454.dat
src/cal_star/refdata/1d_sp/Hamuy1992/hr4468.dat
src/cal_star/refdata/1d_sp/Hamuy1992/hr4963.dat
src/cal_star/refdata/1d_sp/Hamuy1992/hr5501.dat
src/cal_star/refdata/1d_sp/Hamuy1992/hr718.dat
src/cal_star/refdata/1d_sp/Hamuy1992/hr7596.dat
src/cal_star/refdata/1d_sp/Hamuy1992/hr7950.dat
src/cal_star/refdata/1d_sp/Hamuy1992/hr8634.dat
src/cal_star/refdata/1d_sp/Hamuy1992/hr9087.dat
src/cal_star/refdata/1d_sp/Massey1998/BD +28 4211.dat
src/cal_star/refdata/1d_sp/Massey1998/Cyg OB2 No.9.dat
src/cal_star/refdata/1d_sp/Massey1998/EG 81.dat
src/cal_star/refdata/1d_sp/Massey1998/Feige 110.dat
src/cal_star/refdata/1d_sp/Massey1998/Feige 34.dat
src/cal_star/refdata/1d_sp/Massey1998/Feige 66.dat
